pymodaq_plugins_acs_motion/__init__.py
pymodaq_plugins_acs_motion/utils.py
pymodaq_plugins_acs_motion/app/__init__.py
pymodaq_plugins_acs_motion/app/custom_app_template.py
pymodaq_plugins_acs_motion/daq_move_plugins/__init__.py
pymodaq_plugins_acs_motion/daq_move_plugins/daq_move_AcsXY.py
pymodaq_plugins_acs_motion/daq_viewer_plugins/__init__.py
pymodaq_plugins_acs_motion/daq_viewer_plugins/plugins_0D/__init__.py
pymodaq_plugins_acs_motion/daq_viewer_plugins/plugins_1D/__init__.py
pymodaq_plugins_acs_motion/daq_viewer_plugins/plugins_2D/__init__.py
pymodaq_plugins_acs_motion/daq_viewer_plugins/plugins_ND/__init__.py
pymodaq_plugins_acs_motion/exporters/__init__.py
pymodaq_plugins_acs_motion/extensions/__init__.py
pymodaq_plugins_acs_motion/extensions/custom_extension_template.py
pymodaq_plugins_acs_motion/hardware/__init__.py
pymodaq_plugins_acs_motion/hardware/acscontrol.py
pymodaq_plugins_acs_motion/models/PIDModelTemplate.py
pymodaq_plugins_acs_motion/models/__init__.py
pymodaq_plugins_acs_motion/resources/__init__.py
pymodaq_plugins_acs_motion/resources/config_template.toml
pymodaq_plugins_acs_motion/scanners/__init__.py
pymodaq_plugins_acs_motion-1.0.3.dist-info/METADATA
pymodaq_plugins_acs_motion-1.0.3.dist-info/WHEEL
pymodaq_plugins_acs_motion-1.0.3.dist-info/entry_points.txt
pymodaq_plugins_acs_motion-1.0.3.dist-info/licenses/LICENSE
pymodaq_plugins_acs_motion-1.0.3.dist-info/RECORD
